sphinx_autodoc_variants/__init__.py
sphinx_autodoc_variants/_version.py
sphinx_autodoc_variants/variant_autodoc.py
sphinx_autodoc_variants-0.1.0.dist-info/METADATA
sphinx_autodoc_variants-0.1.0.dist-info/RECORD
sphinx_autodoc_variants-0.1.0.dist-info/WHEEL
sphinx_autodoc_variants-0.1.0.dist-info/top_level.txt
